elements/__init__.py
elements/agg.py
elements/checkpoint.py
elements/config.py
elements/counter.py
elements/diskcache.py
elements/flags.py
elements/fps.py
elements/logger.py
elements/path.py
elements/plotting.py
elements/printing.py
elements/rwlock.py
elements/space.py
elements/timer.py
elements/tree.py
elements/usage.py
elements/utils.py
elements/uuid.py
elements/when.py
elements-3.21.0.dist-info/WHEEL
elements-3.21.0.dist-info/METADATA
elements-3.21.0.dist-info/RECORD
