Metadata-Version: 2.4
Name: elements
Version: 3.21.0
Summary: Building blocks for productive research
Author: Danijar Hafner
Author-email: Danijar Hafner <mail@danijar.com>
License-Expression: MIT
Classifier: Intended Audience :: Science/Research
Classifier: Programming Language :: Python :: 3
Requires-Dist: google-auth
Requires-Dist: google-cloud-storage
Requires-Dist: numpy
Requires-Dist: psutil
Requires-Dist: ruamel-yaml
Requires-Dist: gputil ; extra == 'extra'
Requires-Dist: matplotlib ; extra == 'extra'
Requires-Dist: mlflow ; extra == 'extra'
Requires-Dist: pytest ; extra == 'extra'
Requires-Dist: tensorflow-cpu ; extra == 'extra'
Requires-Dist: wandb ; extra == 'extra'
Maintainer: Danijar Hafner
Maintainer-email: Danijar Hafner <mail@danijar.com>
Requires-Python: >=3.10
Project-URL: Homepage, http://github.com/danijar/elements
Provides-Extra: extra
